{
  "id": 15,
  "name": "Grand finale",
  "holes": [
    { "id": "h1", "x": 90, "y": 260, "kind": "board" },
    { "id": "h2", "x": 200, "y": 260, "kind": "board" },
    { "id": "h3", "x": 310, "y": 260, "kind": "board" },
    { "id": "h4", "x": 200, "y": 200, "kind": "board" },
    { "id": "h5", "x": 140, "y": 140, "kind": "board" },
    { "id": "h6", "x": 260, "y": 140, "kind": "board" },
    { "id": "s1", "x": 100, "y": 390, "kind": "stash" },
    { "id": "s2", "x": 200, "y": 390, "kind": "stash" },
    { "id": "s3", "x": 300, "y": 390, "kind": "stash" }
  ],
  "plates": [
    { "id": "base", "layer": 0, "anchors": ["h1", "h2", "h3"], "width": 240, "height": 38 },
    { "id": "mid", "layer": 1, "anchors": ["h2", "h4"], "width": 120, "height": 34 },
    { "id": "top", "layer": 2, "anchors": ["h5", "h6"], "width": 140, "height": 32 }
  ],
  "screws": { "h1": "a", "h2": "b", "h3": "c", "h4": "d", "h5": "e", "h6": "f" }
}
